binexport/__init__.py
binexport/__main__.py
binexport/basic_block.py
binexport/binexport2_pb2.py
binexport/expression.py
binexport/function.py
binexport/instruction.py
binexport/operand.py
binexport/program.py
binexport/types.py
binexport/utils.py
python_binexport-0.4.2.dist-info/licenses/LICENSE
python_binexport-0.4.2.dist-info/METADATA
python_binexport-0.4.2.dist-info/WHEEL
python_binexport-0.4.2.dist-info/entry_points.txt
python_binexport-0.4.2.dist-info/top_level.txt
python_binexport-0.4.2.dist-info/RECORD
