Metadata-Version: 2.4
Name: python-binexport
Version: 0.4.2
Summary: Python wrapper to manipulate binexport files (protobuf)
Author-email: Quarkslab <diffing@quarkslab.com>
License: AGPL-3.0
Project-URL: Homepage, https://github.com/quarkslab/python-binexport
Project-URL: Repository, https://github.com/quarkslab/python-binexport
Project-URL: Documentation, https://quarkslab.github.io/diffing-portal/exporter/binexport.html#python-binexport
Project-URL: Bug Tracker, https://github.com/quarkslab/python-binexport/issues
Classifier: Topic :: Security
Classifier: Environment :: Console
Classifier: Operating System :: OS Independent
Requires-Python: >=3.10
License-File: LICENSE
Requires-Dist: python-magic; os_name != "nt"
Requires-Dist: python-magic-bin; os_name == "nt"
Requires-Dist: click
Requires-Dist: protobuf
Requires-Dist: networkx
Requires-Dist: enum_tools
Requires-Dist: idascript
Provides-Extra: dev
Requires-Dist: tox; extra == "dev"
Dynamic: license-file
